{"list":[{"type":"basic_block","data":{"section_label":"Obedience","prayer":"Jesus, teach the believers in the state of Geta that love for you and obedience to you are connected.","reference":"John 14:15","verse":"If you love me, keep my commands.","id":"fbf33967220396e0af47db156edee2757294ccee47c5a0fe3f122cc12ecc9144"}},{"type":"photo_block","data":{"section_label":"One Shot Prayer Walk","location_label":"Photo from the state of Geta, \u00c5land","url":"https:\/\/storage.googleapis.com\/location-grid-images\/v1\/grid\/100001079\/photos\/cafe_e2ba83ec4d0ff.jpg","section_summary":"What people or resources could you pray for in this photo?","prayer":""}},{"type":"basic_block","data":{"section_label":"Intentional Multiplicative Strategies","prayer":"Jesus, help the church in the state of Geta to not rely on buildings or programs, but on your Spirit and the simple faithfulness of every believer.","reference":"","verse":"","id":"a0defeec61ca7680d7a86fdcc8e270c005aa1e82d1f820a314239d6f7e5410b0"}},{"type":"lost_per_believer","data":{"section_label":"Faith Status","label_1":"One disciple of Jesus for every 83 lost neighbors","lost_per_believer":83,"prayer":""}},{"type":"basic_block","data":{"section_label":"Far from God","prayer":"Father, you desire the people in the state of Geta who are far from you to hear about you.","reference":"Romans 15:21","verse":"&quot;Those who were not told about him will see, and those who have not heard will understand.&quot;","id":"1012c2ad1c18088d29e4c8d498cf45a9b94697753c6dc7ab167ed67baf595807"}},{"type":"basic_block","data":{"section_label":"Evangelists and Harvest Workers","prayer":"Jesus, please give your people in Geta, \u00c5land a passion for the lost.","reference":"2 Corinthians 5:20","verse":"We are therefore Christ\u2019s ambassadors, as though God were making his appeal through us. We implore you on Christ\u2019s behalf: Be reconciled to God.","id":"fa9bcc1aa06b766800413be49b880d645b039449f496ff500741f4814e8a2bff"}},{"type":"basic_block","data":{"section_label":"Biblical Authority","prayer":"Spirit, fill the 6 believers in the state of Geta with tears, because God is not obeyed by those around them.","reference":"Psalm 119:136","verse":"Streams of tears flow from my eyes, for your law is not obeyed.","id":"57973d024c381fa29c7e433302e5b447a5b9ba293db4736b02a3c9a2fecc5c8f"}},{"type":"basic_block","data":{"section_label":"Non-Christians","prayer":"Jesus, please send your Spirit to Geta, so they can have freedom.","reference":"2 Corinthians 3:17","verse":"Now the Lord is the Spirit, and where the Spirit of the Lord is, there is freedom.","id":"56df8ba2ef1b560c7e794a933e1c7c39d5bef79e495d8aa2e877a8433f09b341"}},{"type":"basic_block","data":{"section_label":"Safety","prayer":"Jesus, protect the vulnerable in Geta, \u00c5land from the evil one.","reference":"John 17:15","verse":"My prayer is not that you take them out of the world but that you protect them from the evil one.","id":"a5aa40afc0a1dc28c7c54483b0d82a8a6f4fc00d6cfe27c52831459af6b60a3f"}},{"type":"4_fact_blocks","data":{"section_label":"Demographics","focus_label":"Geta, \u00c5land","label_1":"Non-Christians","value_1":"3","size_1":"two-em","label_2":"Cultural Christians","value_2":"490","size_2":"two-em","label_3":"Believers","value_3":"6","size_3":"two-em","label_4":"Language","value_4":"Swedish","size_4":"two-em","section_summary":"","prayer":""}}],"location":{"grid_id":"100001079","name":"Geta","admin0_name":"\u00c5land","full_name":"Geta, \u00c5land","population":"500","latitude":60.3949,"longitude":19.8434,"country_code":"AX","admin0_code":"ALA","parent_id":"100001074","parent_name":"\u00c5land","admin0_grid_id":"100001074","admin1_grid_id":"100001079","admin1_name":"Geta","admin2_grid_id":null,"admin2_name":null,"admin3_grid_id":null,"admin3_name":null,"admin4_grid_id":null,"admin4_name":null,"admin5_grid_id":null,"admin5_name":null,"level":1,"level_name":"admin1","north_latitude":60.4688,"south_latitude":60.3211,"east_longitude":19.9604,"west_longitude":19.7263,"p_longitude":20.3166,"p_latitude":60.2,"p_north_latitude":60.6521,"p_south_latitude":59.7479,"p_east_longitude":21.3286,"p_west_longitude":19.3047,"c_longitude":20.3166,"c_latitude":60.2,"c_north_latitude":60.6521,"c_south_latitude":59.7479,"c_east_longitude":21.3286,"c_west_longitude":19.3047,"peer_locations":"16","birth_rate":1.68,"death_rate":7.7,"growth_rate":0.9398,"believers":"6","christian_adherents":"490","non_christians":"3","primary_language":"Swedish","primary_religion":"Christianity","percent_believers":1.2,"percent_christian_adherents":98.1,"percent_non_christians":0.7,"admin_level_name":"state","admin_level_title":"the state","admin_level_name_cap":"State","admin_level_name_plural":"states","population_int":500,"believers_int":6,"christian_adherents_int":490,"non_christians_int":3,"percent_believers_full":1.2,"percent_christian_adherents_full":98.1,"percent_non_christians_full":0.7,"all_lost_int":493,"all_lost":"493","lost_per_believer_int":83,"lost_per_believer":"83","population_growth_status":"Fastest Declining in the World","deaths_non_christians_next_hour":"0","deaths_non_christians_next_100":"0","deaths_non_christians_next_week":"0","deaths_non_christians_next_month":"0","deaths_non_christians_next_year":"3","births_non_christians_last_hour":"0","births_non_christians_last_100":"0","births_non_christians_last_week":"0","births_non_christians_last_month":"0","births_non_christians_last_year":"0","deaths_christian_adherents_next_hour":"0","deaths_christian_adherents_next_100":"0","deaths_christian_adherents_next_week":"0","deaths_christian_adherents_next_month":"0","deaths_christian_adherents_next_year":"3","births_christian_adherents_last_hour":"0","births_christian_adherents_last_100":"0","births_christian_adherents_last_week":"0","births_christian_adherents_last_month":"0","births_christian_adherents_last_year":"0","deaths_among_lost":"0","new_churches_needed":"1","favor":"christian_adherents","icon_color":"brand"}}